Metadata-Version: 2.1
Name: sdnn-cl
Version: 2.2.0
Summary: SDNN: An End to End Tensor IR/DSL Stack for Deep Learning Systems
Home-page: https://github.com/apache/tvm
License: UNKNOWN
Platform: UNKNOWN
Provides-Extra: ethosu
Provides-Extra: importer-caffe2
Provides-Extra: importer-coreml
Provides-Extra: importer-darknet
Provides-Extra: importer-keras
Provides-Extra: importer-onnx
Provides-Extra: importer-paddle
Provides-Extra: importer-pytorch
Provides-Extra: importer-tensorflow
Provides-Extra: importer-tflite
Provides-Extra: tvmc
Provides-Extra: vitis-ai
Provides-Extra: xgboost
Provides-Extra: dev
Provides-Extra: all-prod
